JJCale/__init__.py
JJCale/app.py
JJCale/middlewares.py
JJCale/response.py
JJCale/router.py
JJCale-0.1.dist-info/METADATA
JJCale-0.1.dist-info/WHEEL
JJCale-0.1.dist-info/top_level.txt
JJCale-0.1.dist-info/RECORD
