Metadata-Version: 2.1
Name: JJCale
Version: 0.1
Summary: a simple web framework
Home-page: https://github.com/lrhhhhhh/JJCale
Author: lrhaoo
License: MIT
Keywords: web,framework
Platform: UNKNOWN
Classifier: Programming Language :: Python :: 3
Classifier: License :: OSI Approved :: MIT License
Requires-Python: >=3.6
Requires-Dist: Werkzeug (>=2.0.0)
Requires-Dist: jinja2 (>=3.0.0)
